PyFraction/__init__.py
PyFraction/fraction.py
PyFraction-0.1.dist-info/METADATA
PyFraction-0.1.dist-info/WHEEL
PyFraction-0.1.dist-info/top_level.txt
PyFraction-0.1.dist-info/RECORD
