Metadata-Version: 2.1
Name: PyFraction
Version: 0.1
Summary: Fraction Datatype
Home-page: UNKNOWN
Author: theAbMan
License: UNKNOWN
Platform: UNKNOWN
